libfranco/__init__.py
libfranco/tdms_grafico.py
libfranco-2.0.1.dist-info/LICENSE
libfranco-2.0.1.dist-info/METADATA
libfranco-2.0.1.dist-info/WHEEL
libfranco-2.0.1.dist-info/top_level.txt
libfranco-2.0.1.dist-info/RECORD
