Metadata-Version: 2.1
Name: libfranco
Version: 2.0.1
Summary: Libreria per gestire TDMS e grafici
Home-page: https://pypi.org/project/libfranco/
Author: Franco De Angelis
Author-email: fd23111991@gmail.com
Classifier: Programming Language :: Python :: 3
Classifier: License :: OSI Approved :: MIT License
Classifier: Operating System :: OS Independent
Requires-Python: >=3.6
License-File: LICENSE
Requires-Dist: nptdms
Requires-Dist: matplotlib
Requires-Dist: pandas
Requires-Dist: numpy
Requires-Dist: scipy
